morpcc
