Metadata-Version: 1.0
Name: morpcc
Version: 0.1.0a4
Summary: Morp Control Center
Home-page: http://github.com/morpframework/morpcc
Author: Izhar Firdaus
Author-email: kagesenshi.87@gmail.com
License: GPLv3
Keywords: framework cms
Platform: UNKNOWN
